NetHyTech_STT_aditya_s/__init__.py
nethytech_stt_aditya_s-0.1.dist-info/METADATA
nethytech_stt_aditya_s-0.1.dist-info/WHEEL
nethytech_stt_aditya_s-0.1.dist-info/top_level.txt
nethytech_stt_aditya_s-0.1.dist-info/RECORD
