Metadata-Version: 2.4
Name: NetHyTech-Stt_aditya_s
Version: 0.1
Summary: this is speech to text package created by aditya sharma
Author: Aditya Sharma
Author-email: aadityasharma38535@gmail.com
Dynamic: author
Dynamic: author-email
Dynamic: summary
